backtest_ape/__about__.py
backtest_ape/__init__.py
backtest_ape/base.py
backtest_ape/py.typed
backtest_ape/setup.py
backtest_ape/utils.py
backtest_ape/curve/__init__.py
backtest_ape/curve/v2/__init__.py
backtest_ape/curve/v2/base.py
backtest_ape/curve/v2/lp.py
backtest_ape/curve/v2/setup.py
backtest_ape/uniswap/__init__.py
backtest_ape/uniswap/v3/__init__.py
backtest_ape/uniswap/v3/base.py
backtest_ape/uniswap/v3/lp.py
backtest_ape/uniswap/v3/setup.py
backtest_ape-0.1.0.dist-info/METADATA
backtest_ape-0.1.0.dist-info/WHEEL
backtest_ape-0.1.0.dist-info/licenses/LICENSE
backtest_ape-0.1.0.dist-info/RECORD
