Metadata-Version: 2.1
Name: backtest-ape
Version: 0.1.0
Summary: Backtesting and forward-testing (via Monte Carlo sims) for DeFi strategies.
Project-URL: Documentation, https://github.com/smolquants/backtest-ape#readme
Project-URL: Issues, https://github.com/smolquants/backtest-ape/issues
Project-URL: Source, https://github.com/smolquants/backtest-ape
Author-email: smolquants <dev@smolquants.xyz>
License-Expression: MIT
License-File: LICENSE
Classifier: Development Status :: 4 - Beta
Classifier: Programming Language :: Python
Classifier: Programming Language :: Python :: 3.8
Classifier: Programming Language :: Python :: 3.9
Classifier: Programming Language :: Python :: 3.10
Classifier: Programming Language :: Python :: Implementation :: CPython
Classifier: Programming Language :: Python :: Implementation :: PyPy
Requires-Python: <3.11,>=3.8
Requires-Dist: eth-ape<0.6.0,>=0.5.8
Requires-Dist: hypothesis<7.0,>=6.2.0
Requires-Dist: matplotlib
Requires-Dist: numpy<2.0,>=1.21
Requires-Dist: pandas
Requires-Dist: scipy
Requires-Dist: typing-inspect==0.8.0
